Workbook

Sheet Assessment Instructions
A1: AI Opportunity Assessment v1.0
A2: Each user to review only AI Opportunities relevant to his or her domain. Leadership scores all.
A3: Each factor needs to be weighted appropriately in the overall scores calculation. Impact & Feasibility would have defined weightage in calculating AI Opportunity score
A4: Factors should be such that targeted users can score the opportunities effectively
A5: Scoring to be done by AI CoE team basis interview with relevant initiative business owners

Sheet Assessment Template
E1: Impact | I1: Feasibility
A2: Business Area | B2: AI Opportunity | C2: Business Goal | D2: Relevant Team | E2: Financial Impact (Revenue or Margin Growth, Losses Prevented) | F2: Process Efficiency (Reduce process time, reduce error rate) | G2: Customer Experience (CLV or NPS Growth) | H2: Strategic Priority | I2: Data Readiness | J2: Process Readiness | K2: Implementation Complexity (System/Teams involved) | L2: Risk Profile | M2: CapEx Cost | N2: OpEx Cost | O2: Impact Score | P2: Feasibility Score | Q2: AI Opportunity Score
A3: Supply Chain | B3: Demand Forecasting | C3: Reduce Cost | D3: Supply Chain, Planning | O3: =E3*Weights!$B$2+'Assessment Template'!F3*Weights!$B$3+'Assessment Template'!G3*Weights!$B$4+'Assessment Template'!H3*Weights!$B$5 | P3: =I3*Weights!$B$8+J3*Weights!$B$9+(100-'Assessment Template'!K3)*Weights!$B$10+(100-'Assessment Template'!L3)*Weights!$B$11+(100-'Assessment Template'!M3)*Weights!$B$12+(100-'Assessment Template'!N3)*Weights!$B$13 | Q3: =O3*Weights!$B$16+(P3*Weights!$B$17)
A4: Supply Chain | B4: Inventory Optimization | C4: Reduce Cost | D4: Supply Chain, Merchandising | O4: =E4*Weights!$B$2+'Assessment Template'!F4*Weights!$B$3+'Assessment Template'!G4*Weights!$B$4+'Assessment Template'!H4*Weights!$B$5 | P4: =I4*Weights!$B$8+J4*Weights!$B$9+(100-'Assessment Template'!K4)*Weights!$B$10+(100-'Assessment Template'!L4)*Weights!$B$11+(100-'Assessment Template'!M4)*Weights!$B$12+(100-'Assessment Template'!N4)*Weights!$B$13 | Q4: =O4*Weights!$B$16+(P4*Weights!$B$17)
A5: Supply Chain | B5: Automated Replenishment Recommendations | C5: Improve Operational Efficiency | D5: Supply Chain | O5: =E5*Weights!$B$2+'Assessment Template'!F5*Weights!$B$3+'Assessment Template'!G5*Weights!$B$4+'Assessment Template'!H5*Weights!$B$5 | P5: =I5*Weights!$B$8+J5*Weights!$B$9+(100-'Assessment Template'!K5)*Weights!$B$10+(100-'Assessment Template'!L5)*Weights!$B$11+(100-'Assessment Template'!M5)*Weights!$B$12+(100-'Assessment Template'!N5)*Weights!$B$13 | Q5: =O5*Weights!$B$16+(P5*Weights!$B$17)
A6: Supply Chain | B6: Stock Transfer Optimization | C6: Reduce Cost | D6: Supply Chain, Logistics | O6: =E6*Weights!$B$2+'Assessment Template'!F6*Weights!$B$3+'Assessment Template'!G6*Weights!$B$4+'Assessment Template'!H6*Weights!$B$5 | P6: =I6*Weights!$B$8+J6*Weights!$B$9+(100-'Assessment Template'!K6)*Weights!$B$10+(100-'Assessment Template'!L6)*Weights!$B$11+(100-'Assessment Template'!M6)*Weights!$B$12+(100-'Assessment Template'!N6)*Weights!$B$13 | Q6: =O6*Weights!$B$16+(P6*Weights!$B$17)
A7: Supply Chain | B7: Supplier Risk Monitoring | C7: Reduce Risk | D7: Procurement | O7: =E7*Weights!$B$2+'Assessment Template'!F7*Weights!$B$3+'Assessment Template'!G7*Weights!$B$4+'Assessment Template'!H7*Weights!$B$5 | P7: =I7*Weights!$B$8+J7*Weights!$B$9+(100-'Assessment Template'!K7)*Weights!$B$10+(100-'Assessment Template'!L7)*Weights!$B$11+(100-'Assessment Template'!M7)*Weights!$B$12+(100-'Assessment Template'!N7)*Weights!$B$13 | Q7: =O7*Weights!$B$16+(P7*Weights!$B$17)
A8: Supply Chain | B8: Distribution Center Labor Optimization | C8: Improve Operational Efficiency | D8: Distribution Operations | O8: =E8*Weights!$B$2+'Assessment Template'!F8*Weights!$B$3+'Assessment Template'!G8*Weights!$B$4+'Assessment Template'!H8*Weights!$B$5 | P8: =I8*Weights!$B$8+J8*Weights!$B$9+(100-'Assessment Template'!K8)*Weights!$B$10+(100-'Assessment Template'!L8)*Weights!$B$11+(100-'Assessment Template'!M8)*Weights!$B$12+(100-'Assessment Template'!N8)*Weights!$B$13 | Q8: =O8*Weights!$B$16+(P8*Weights!$B$17)
A9: Store & Retail Operations | B9: Workforce Scheduling Optimization | C9: Reduce Cost | D9: Store Operations | O9: =E9*Weights!$B$2+'Assessment Template'!F9*Weights!$B$3+'Assessment Template'!G9*Weights!$B$4+'Assessment Template'!H9*Weights!$B$5 | P9: =I9*Weights!$B$8+J9*Weights!$B$9+(100-'Assessment Template'!K9)*Weights!$B$10+(100-'Assessment Template'!L9)*Weights!$B$11+(100-'Assessment Template'!M9)*Weights!$B$12+(100-'Assessment Template'!N9)*Weights!$B$13 | Q9: =O9*Weights!$B$16+(P9*Weights!$B$17)
A10: Store & Retail Operations | B10: Store Manager Copilot | C10: Improve Employee Productivity | D10: Store Operations | O10: =E10*Weights!$B$2+'Assessment Template'!F10*Weights!$B$3+'Assessment Template'!G10*Weights!$B$4+'Assessment Template'!H10*Weights!$B$5 | P10: =I10*Weights!$B$8+J10*Weights!$B$9+(100-'Assessment Template'!K10)*Weights!$B$10+(100-'Assessment Template'!L10)*Weights!$B$11+(100-'Assessment Template'!M10)*Weights!$B$12+(100-'Assessment Template'!N10)*Weights!$B$13 | Q10: =O10*Weights!$B$16+(P10*Weights!$B$17)
A11: Store & Retail Operations | B11: Task Prioritization Assistant | C11: Improve Operational Efficiency | D11: Store Operations | O11: =E11*Weights!$B$2+'Assessment Template'!F11*Weights!$B$3+'Assessment Template'!G11*Weights!$B$4+'Assessment Template'!H11*Weights!$B$5 | P11: =I11*Weights!$B$8+J11*Weights!$B$9+(100-'Assessment Template'!K11)*Weights!$B$10+(100-'Assessment Template'!L11)*Weights!$B$11+(100-'Assessment Template'!M11)*Weights!$B$12+(100-'Assessment Template'!N11)*Weights!$B$13 | Q11: =O11*Weights!$B$16+(P11*Weights!$B$17)
A12: Store & Retail Operations | B12: Loss Prevention Anomaly Detection | C12: Reduce Risk | D12: Asset Protection | O12: =E12*Weights!$B$2+'Assessment Template'!F12*Weights!$B$3+'Assessment Template'!G12*Weights!$B$4+'Assessment Template'!H12*Weights!$B$5 | P12: =I12*Weights!$B$8+J12*Weights!$B$9+(100-'Assessment Template'!K12)*Weights!$B$10+(100-'Assessment Template'!L12)*Weights!$B$11+(100-'Assessment Template'!M12)*Weights!$B$12+(100-'Assessment Template'!N12)*Weights!$B$13 | Q12: =O12*Weights!$B$16+(P12*Weights!$B$17)
A13: Store & Retail Operations | B13: In-Store Associate Copilot | C13: Improve Customer Experience | D13: Store Operations | O13: =E13*Weights!$B$2+'Assessment Template'!F13*Weights!$B$3+'Assessment Template'!G13*Weights!$B$4+'Assessment Template'!H13*Weights!$B$5 | P13: =I13*Weights!$B$8+J13*Weights!$B$9+(100-'Assessment Template'!K13)*Weights!$B$10+(100-'Assessment Template'!L13)*Weights!$B$11+(100-'Assessment Template'!M13)*Weights!$B$12+(100-'Assessment Template'!N13)*Weights!$B$13 | Q13: =O13*Weights!$B$16+(P13*Weights!$B$17)
A14: Store & Retail Operations | B14: Energy Consumption Optimization | C14: Reduce Cost | D14: Facilities | O14: =E14*Weights!$B$2+'Assessment Template'!F14*Weights!$B$3+'Assessment Template'!G14*Weights!$B$4+'Assessment Template'!H14*Weights!$B$5 | P14: =I14*Weights!$B$8+J14*Weights!$B$9+(100-'Assessment Template'!K14)*Weights!$B$10+(100-'Assessment Template'!L14)*Weights!$B$11+(100-'Assessment Template'!M14)*Weights!$B$12+(100-'Assessment Template'!N14)*Weights!$B$13 | Q14: =O14*Weights!$B$16+(P14*Weights!$B$17)
... A26: eCommerce | B26: AI Style Advisor | C26: Win Younger Audience | D26: Digital Commerce, Marketing | O26: =E26*Weights!$B$2+'Assessment Template'!F26*Weights!$B$3+'Assessment Template'!G26*Weights!$B$4+'Assessment Template'!H26*Weights!$B$5 | P26: =I26*Weights!$B$8+J26*Weights!$B$9+(100-'Assessment Template'!K26)*Weights!$B$10+(100-'Assessment Template'!L26)*Weights!$B$11+(100-'Assessment Template'!M26)*Weights!$B$12+(100-'Assessment Template'!N26)*Weights!$B$13 | Q26: =O26*Weights!$B$16+(P26*Weights!$B$17)
A27: Finance | B27: BLP | C27: Reduce cost & errors involved in processing invoice | D27: Finance | E27: 20 | F27: 20 | G27: 0 | H27: 0 | I27: 100 | J27: 20 | K27: 65 | L27: 35 | M27: 10 | N27: 35 | O27: =E27*Weights!$B$2+'Assessment Template'!F27*Weights!$B$3+'Assessment Template'!G27*Weights!$B$4+'Assessment Template'!H27*Weights!$B$5 | P27: =I27*Weights!$B$8+J27*Weights!$B$9+(100-'Assessment Template'!K27)*Weights!$B$10+(100-'Assessment Template'!L27)*Weights!$B$11+(100-'Assessment Template'!M27)*Weights!$B$12+(100-'Assessment Template'!N27)*Weights!$B$13 | Q27: =O27*Weights!$B$16+(P27*Weights!$B$17)
A28: Finance | B28: Invoice Processing Automation | C28: Reduce Cost | D28: Finance | O28: =E28*Weights!$B$2+'Assessment Template'!F28*Weights!$B$3+'Assessment Template'!G28*Weights!$B$4+'Assessment Template'!H28*Weights!$B$5 | P28: =I28*Weights!$B$8+J28*Weights!$B$9+(100-'Assessment Template'!K28)*Weights!$B$10+(100-'Assessment Template'!L28)*Weights!$B$11+(100-'Assessment Template'!M28)*Weights!$B$12+(100-'Assessment Template'!N28)*Weights!$B$13 | Q28: =O28*Weights!$B$16+(P28*Weights!$B$17)
A29: Finance | B29: Financial Close Copilot | C29: Improve Operational Efficiency | D29: Finance | O29: =E29*Weights!$B$2+'Assessment Template'!F29*Weights!$B$3+'Assessment Template'!G29*Weights!$B$4+'Assessment Template'!H29*Weights!$B$5 | P29: =I29*Weights!$B$8+J29*Weights!$B$9+(100-'Assessment Template'!K29)*Weights!$B$10+(100-'Assessment Template'!L29)*Weights!$B$11+(100-'Assessment Template'!M29)*Weights!$B$12+(100-'Assessment Template'!N29)*Weights!$B$13 | Q29: =O29*Weights!$B$16+(P29*Weights!$B$17)
A30: Finance | B30: Fraud & Anomaly Detection | C30: Reduce Risk | D30: Finance | O30: =E30*Weights!$B$2+'Assessment Template'!F30*Weights!$B$3+'Assessment Template'!G30*Weights!$B$4+'Assessment Template'!H30*Weights!$B$5 | P30: =I30*Weights!$B$8+J30*Weights!$B$9+(100-'Assessment Template'!K30)*Weights!$B$10+(100-'Assessment Template'!L30)*Weights!$B$11+(100-'Assessment Template'!M30)*Weights!$B$12+(100-'Assessment Template'!N30)*Weights!$B$13 | Q30: =O30*Weights!$B$16+(P30*Weights!$B$17)
A31: Finance | B31: Cash Flow Forecasting | C31: Improve Planning | D31: FP&A | O31: =E31*Weights!$B$2+'Assessment Template'!F31*Weights!$B$3+'Assessment Template'!G31*Weights!$B$4+'Assessment Template'!H31*Weights!$B$5 | P31: =I31*Weights!$B$8+J31*Weights!$B$9+(100-'Assessment Template'!K31)*Weights!$B$10+(100-'Assessment Template'!L31)*Weights!$B$11+(100-'Assessment Template'!M31)*Weights!$B$12+(100-'Assessment Template'!N31)*Weights!$B$13 | Q31: =O31*Weights!$B$16+(P31*Weights!$B$17)
A32: Finance | B32: Vendor Spend Optimization | C32: Reduce Cost | D32: Procurement / Finance | O32: =E32*Weights!$B$2+'Assessment Template'!F32*Weights!$B$3+'Assessment Template'!G32*Weights!$B$4+'Assessment Template'!H32*Weights!$B$5 | P32: =I32*Weights!$B$8+J32*Weights!$B$9+(100-'Assessment Template'!K32)*Weights!$B$10+(100-'Assessment Template'!L32)*Weights!$B$11+(100-'Assessment Template'!M32)*Weights!$B$12+(100-'Assessment Template'!N32)*Weights!$B$13 | Q32: =O32*Weights!$B$16+(P32*Weights!$B$17)
A33: Finance | B33: Finance Analyst Copilot | C33: Improve Employee Productivity | D33: Finance | O33: =E33*Weights!$B$2+'Assessment Template'!F33*Weights!$B$3+'Assessment Template'!G33*Weights!$B$4+'Assessment Template'!H33*Weights!$B$5 | P33: =I33*Weights!$B$8+J33*Weights!$B$9+(100-'Assessment Template'!K33)*Weights!$B$10+(100-'Assessment Template'!L33)*Weights!$B$11+(100-'Assessment Template'!M33)*Weights!$B$12+(100-'Assessment Template'!N33)*Weights!$B$13 | Q33: =O33*Weights!$B$16+(P33*Weights!$B$17)
A34: Customer Care | B34: Customer Service Chatbot | C34: Reduce Cost | D34: Customer Care | O34: =E34*Weights!$B$2+'Assessment Template'!F34*Weights!$B$3+'Assessment Template'!G34*Weights!$B$4+'Assessment Template'!H34*Weights!$B$5 | P34: =I34*Weights!$B$8+J34*Weights!$B$9+(100-'Assessment Template'!K34)*Weights!$B$10+(100-'Assessment Template'!L34)*Weights!$B$11+(100-'Assessment Template'!M34)*Weights!$B$12+(100-'Assessment Template'!N34)*Weights!$B$13 | Q34: =O34*Weights!$B$16+(P34*Weights!$B$17)
A35: Customer Care | B35: Agent Assist Copilot | C35: Improve Customer Experience | D35: Customer Care | O35: =E35*Weights!$B$2+'Assessment Template'!F35*Weights!$B$3+'Assessment Template'!G35*Weights!$B$4+'Assessment Template'!H35*Weights!$B$5 | P35: =I35*Weights!$B$8+J35*Weights!$B$9+(100-'Assessment Template'!K35)*Weights!$B$10+(100-'Assessment Template'!L35)*Weights!$B$11+(100-'Assessment Template'!M35)*Weights!$B$12+(100-'Assessment Template'!N35)*Weights!$B$13 | Q35: =O35*Weights!$B$16+(P35*Weights!$B$17)
A36: Customer Care | B36: Case Summarization | C36: Improve Operational Efficiency | D36: Customer Care | O36: =E36*Weights!$B$2+'Assessment Template'!F36*Weights!$B$3+'Assessment Template'!G36*Weights!$B$4+'Assessment Template'!H36*Weights!$B$5 | P36: =I36*Weights!$B$8+J36*Weights!$B$9+(100-'Assessment Template'!K36)*Weights!$B$10+(100-'Assessment Template'!L36)*Weights!$B$11+(100-'Assessment Template'!M36)*Weights!$B$12+(100-'Assessment Template'!N36)*Weights!$B$13 | Q36: =O36*Weights!$B$16+(P36*Weights!$B$17)
A37: Customer Care | B37: Proactive Customer Issue Resolution | C37: Increase Loyalty | D37: Customer Care | O37: =E37*Weights!$B$2+'Assessment Template'!F37*Weights!$B$3+'Assessment Template'!G37*Weights!$B$4+'Assessment Template'!H37*Weights!$B$5 | P37: =I37*Weights!$B$8+J37*Weights!$B$9+(100-'Assessment Template'!K37)*Weights!$B$10+(100-'Assessment Template'!L37)*Weights!$B$11+(100-'Assessment Template'!M37)*Weights!$B$12+(100-'Assessment Template'!N37)*Weights!$B$13 | Q37: =O37*Weights!$B$16+(P37*Weights!$B$17)
A38: Customer Care | B38: Contact Center Demand Forecasting | C38: Reduce Cost | D38: Customer Care | O38: =E38*Weights!$B$2+'Assessment Template'!F38*Weights!$B$3+'Assessment Template'!G38*Weights!$B$4+'Assessment Template'!H38*Weights!$B$5 | P38: =I38*Weights!$B$8+J38*Weights!$B$9+(100-'Assessment Template'!K38)*Weights!$B$10+(100-'Assessment Template'!L38)*Weights!$B$11+(100-'Assessment Template'!M38)*Weights!$B$12+(100-'Assessment Template'!N38)*Weights!$B$13 | Q38: =O38*Weights!$B$16+(P38*Weights!$B$17)
A39: Customer Care | B39: Voice-of-Customer Insights Engine | C39: Improve Customer Experience | D39: Customer Care | O39: =E39*Weights!$B$2+'Assessment Template'!F39*Weights!$B$3+'Assessment Template'!G39*Weights!$B$4+'Assessment Template'!H39*Weights!$B$5 | P39: =I39*Weights!$B$8+J39*Weights!$B$9+(100-'Assessment Template'!K39)*Weights!$B$10+(100-'Assessment Template'!L39)*Weights!$B$11+(100-'Assessment Template'!M39)*Weights!$B$12+(100-'Assessment Template'!N39)*Weights!$B$13 | Q39: =O39*Weights!$B$16+(P39*Weights!$B$17)
B40: Password Resets | O40: =E40*Weights!$B$2+'Assessment Template'!F40*Weights!$B$3+'Assessment Template'!G40*Weights!$B$4+'Assessment Template'!H40*Weights!$B$5 | P40: =I40*Weights!$B$8+J40*Weights!$B$9+(100-'Assessment Template'!K40)*Weights!$B$10+(100-'Assessment Template'!L40)*Weights!$B$11+(100-'Assessment Template'!M40)*Weights!$B$12+(100-'Assessment Template'!N40)*Weights!$B$13 | Q40: =O40*Weights!$B$16+(P40*Weights!$B$17)
B41: AI Tools | O41: =E41*Weights!$B$2+'Assessment Template'!F41*Weights!$B$3+'Assessment Template'!G41*Weights!$B$4+'Assessment Template'!H41*Weights!$B$5 | P41: =I41*Weights!$B$8+J41*Weights!$B$9+(100-'Assessment Template'!K41)*Weights!$B$10+(100-'Assessment Template'!L41)*Weights!$B$11+(100-'Assessment Template'!M41)*Weights!$B$12+(100-'Assessment Template'!N41)*Weights!$B$13 | Q41: =O41*Weights!$B$16+(P41*Weights!$B$17)
B42: IMAI POC | O42: =E42*Weights!$B$2+'Assessment Template'!F42*Weights!$B$3+'Assessment Template'!G42*Weights!$B$4+'Assessment Template'!H42*Weights!$B$5 | P42: =I42*Weights!$B$8+J42*Weights!$B$9+(100-'Assessment Template'!K42)*Weights!$B$10+(100-'Assessment Template'!L42)*Weights!$B$11+(100-'Assessment Template'!M42)*Weights!$B$12+(100-'Assessment Template'!N42)*Weights!$B$13 | Q42: =O42*Weights!$B$16+(P42*Weights!$B$17)
B43: Infocepts | O43: =E43*Weights!$B$2+'Assessment Template'!F43*Weights!$B$3+'Assessment Template'!G43*Weights!$B$4+'Assessment Template'!H43*Weights!$B$5 | P43: =I43*Weights!$B$8+J43*Weights!$B$9+(100-'Assessment Template'!K43)*Weights!$B$10+(100-'Assessment Template'!L43)*Weights!$B$11+(100-'Assessment Template'!M43)*Weights!$B$12+(100-'Assessment Template'!N43)*Weights!$B$13 | Q43: =O43*Weights!$B$16+(P43*Weights!$B$17)
B44: New Arc | O44: =E44*Weights!$B$2+'Assessment Template'!F44*Weights!$B$3+'Assessment Template'!G44*Weights!$B$4+'Assessment Template'!H44*Weights!$B$5 | P44: =I44*Weights!$B$8+J44*Weights!$B$9+(100-'Assessment Template'!K44)*Weights!$B$10+(100-'Assessment Template'!L44)*Weights!$B$11+(100-'Assessment Template'!M44)*Weights!$B$12+(100-'Assessment Template'!N44)*Weights!$B$13 | Q44: =O44*Weights!$B$16+(P44*Weights!$B$17)

Sheet Rubric
A1: Factor | B1: Question | C1: 0 | D1: 5 | E1: 20 | F1: 50 | G1: 100
A2: Financial Impact (revenue/margin growth, loss prevention) | B2: How much annual financial impact (revenue, margin, or loss prevention) does this deliver? | C2: Not measurable | D2: <$100K annually | E2: $100–500K annually | F2: $500K–$2M annually | G2: > $2M annually
A3: Process Efficiency (Reduce process time, reduce error rate) | B3: By how much does this reduce process time or error rate? | C3: No change in process time or errors | D3: <5% process time or errors reduced | E3: 5–15% process time or error reduced | F3: 15–50% process time or errors reduced | G3: >50% cut, or process eliminated / straight-through
A4: Customer Experience (CLV or NPS growth) | B4: How much will this move NPS or CLV, and is it in a core customer journey? | C4: No customer-facing change | D4: No NPS or CLV movement (Improves a non-core journey) | E4: <1 NPS or <1% CLV movement (Improves a non-core journey) | F4: +1–5 NPS or +1–2% CLV (Improve in core journey) | G4: +5–10 NPS or +2–5% CLV (Potential to radically improve CX Experience)
A5: Strategic Priority | B5: How directly does this connect to a named FY strategic priority? | C5: Serves no FY strategic priority | D5: Indirectly supports a future FY strategic priority | E5: Indirectly supports a FY strategic priority | F5: Directly serves a FY strategic priority | G5: Required as part of the FY enterprise strategy
A6: Data Readiness | B6: How available and structured is the data required for this initiative? | C6: Data doesn't exist and needs to be captured | D6: Partial data, poorly structured | E6: Partial and reasonably structured data with material gaps | F6: Complete data available and structured | G6: Complete data available which is structured, production-grade, real-time, and governed
A7: Process Readiness | B7: How defined is the process currently? | C7: No defined process, adhoc work with no owner | D7: Informal and person-dependent. No documentation or named owner | E7: Partially defined. An owner is identifiable and informal documentation. | F7: Documented and followed consistently across the function with named owner and measured periodically | G7: Standardised and instrumented. Measured continuously. Named owner carries this outcome in their objectives
A8: Implementation Complexity (Systems / Teams involved) | B8: How many systems and teams does this need to integrate or coordinate across? | C8: No system integrations, only configurations in existing system | D8: Single integration with no dependencies on other teams | E8: Single Integration with multiple dependencies on other teams | F8: Multiple Integrations with multiple dependencies on other teams | G8: Multi system, multi team, multi year transformational implementation
A9: Risk Profile | B9: How much human oversight is there, is it reversible, and who is affected if it goes wrong: internal, customers, or legally/financially? | C9: Back office with no customer or employee decisioning. Fully reversible | D9: Internal decision support with human in the loop. No special review required. | E9: Internal but affects employee outcomes. Needs standard reviews mechanism. | F9: Automated business output reaches customers after legal, brand or internal sign off | G9: Irreversible system actions with potential to disrupt customer experience or company operations or Legal issues
A10: CapEx Cost | B10: What incremental CapEx does this require? | C10: None, Absorbed in existing licenses | D10: <$100k | E10: $100–300K | F10: $300K–$500K | G10: > $500K

Sheet Weights
A1: Impact Score
A2: Financial Impact (revenue/margin growth, loss prevention) | B2: 0.5
A3: Process Efficiency (Reduce process time, reduce error rate) | B3: 0.1
A4: Customer Experience (CLV or NPS growth) | B4: 0.2
A5: Strategic Priority | B5: 0.2
A7: Feasibility Score
A8: Data Readiness | B8: 0.4
A9: Process Readiness | B9: 0.1
A10: Implementation Complexity (Systems / Teams involved) | B10: 0.1
A11: Risk Profile | B11: 0.2
A12: CapEx Cost | B12: 0.2
A14: AI Opportunity Score
A15: Impact Score | B15: 0.6
A16: Feasibility Score | B16: 0.4
